zephony/__init__.py
zephony/decorators.py
zephony/exceptions.py
zephony/helpers.py
zephony/validators.py
zephony/models/__init__.py
zephony-1.11.dist-info/METADATA
zephony-1.11.dist-info/WHEEL
zephony-1.11.dist-info/top_level.txt
zephony-1.11.dist-info/RECORD
