Metadata-Version: 2.1
Name: zephony
Version: 1.11
Summary: Helpers for Python web development
Home-page: https://github.com/Zephony/zephony-pypi
Author: Kevin Isaac
Author-email: kevin@zephony.com
Keywords: zephony,helpers,web
Requires-Dist: voluptuous
Requires-Dist: twilio
